[
  {
    "date": "Jan 1, 2024",
    "observation_period": "5AM - 5AM",
    "eruption": {
      "count": 0,
      "type": null,
      "duration_in_seconds": null
    },
    "seismicity": {
      "volcanic_earthquakes": 17,
      "rockfall_events": 0
    },
    "crater_glow": null,
    "sulfur_dioxide": {
      "date": "Dec 31, 2023",
      "count": {
        "metric_tons": 895,
        "kilograms": 895000
      }
    },
    "plume": {
      "emission": "Moderate",
      "height": {
        "meters": 500,
        "feet": 1640.5
      },
      "drift_direction": [
        "West-Southwest",
        "West-Northwest"
      ]
    },
    "ground_deformation": "Short-term inflation of the edifice",
    "alert_level": {
      "level": 2,
      "remarks": "Decreased Unrest"
    },
    "url": "https://phivolcs.dost.gov.ph/volcano-hazard/volcano-bulletin2/mayon-volcano/22035-mayon-volcano-summary-of-24hr-observation-01-january-2024-5-00-am"
  },
  {
    "date": "Jan 2, 2024",
    "observation_period": "5AM - 5AM",
    "eruption": {
      "count": 0,
      "type": null,
      "duration_in_seconds": null
    },
    "seismicity": {
      "volcanic_earthquakes": 3,
      "rockfall_events": 1
    },
    "crater_glow": null,
    "sulfur_dioxide": {
      "date": "Dec 31, 2023",
      "count": {
        "metric_tons": 895,
        "kilograms": 895000
      }
    },
    "plume": {
      "emission": "Moderate",
      "height": {
        "meters": 1500,
        "feet": 4921.5
      },
      "drift_direction": [
        "West-Northwest",
        "Northwest",
        "North"
      ]
    },
    "ground_deformation": "Short-term inflation of the edifice",
    "alert_level": {
      "level": 2,
      "remarks": "Decreased Unrest"
    },
    "url": "https://phivolcs.dost.gov.ph/volcano-hazard/volcano-bulletin2/mayon-volcano/22051-mayon-volcano-summary-of-24hr-observation-02-january-2024-5-00-am"
  },
  {
    "date": "Jan 3, 2024",
    "observation_period": "12AM - 12AM",
    "eruption": {
      "count": 0,
      "type": null,
      "duration_in_seconds": null
    },
    "seismicity": {
      "volcanic_earthquakes": 3,
      "rockfall_events": 1
    },
    "crater_glow": null,
    "sulfur_dioxide": {
      "date": "Dec 31, 2023",
      "count": {
        "metric_tons": 895,
        "kilograms": 895000
      }
    },
    "plume": {
      "emission": "Moderate",
      "height": {
        "meters": 1000,
        "feet": 3281.0
      },
      "drift_direction": [
        "General West",
        "General North"
      ]
    },
    "ground_deformation": "Short-term inflation of the edifice",
    "alert_level": {
      "level": 2,
      "remarks": "Decreased Unrest"
    },
    "url": "https://phivolcs.dost.gov.ph/volcano-hazard/volcano-bulletin2/mayon-volcano/22069-mayon-volcano-summary-of-24hr-observation-03-january-2024-12-00-am"
  },
  {
    "date": "Jan 4, 2024",
    "observation_period": "12AM - 12AM",
    "eruption": {
      "count": 0,
      "type": null,
      "duration_in_seconds": null
    },
    "seismicity": {
      "volcanic_earthquakes": 2,
      "rockfall_events": 1
    },
    "crater_glow": null,
    "sulfur_dioxide": {
      "date": "Dec 31, 2023",
      "count": {
        "metric_tons": 895,
        "kilograms": 895000
      }
    },
    "plume": {
      "emission": "Moderate",
      "height": {
        "meters": 1000,
        "feet": 3281.0
      },
      "drift_direction": [
        "East-Southeast. East-Northeast"
      ]
    },
    "ground_deformation": "Short-term inflation of the edifice",
    "alert_level": {
      "level": 2,
      "remarks": "Decreased Unrest"
    },
    "url": "https://phivolcs.dost.gov.ph/volcano-hazard/volcano-bulletin2/mayon-volcano/22089-mayon-volcano-summary-of-24hr-observation-04-january-2024-12-00-am"
  },
  {
    "date": "Jan 5, 2024",
    "observation_period": "12AM - 12AM",
    "eruption": {
      "count": 0,
      "type": null,
      "duration_in_seconds": null
    },
    "seismicity": {
      "volcanic_earthquakes": 3,
      "rockfall_events": 2
    },
    "crater_glow": null,
    "sulfur_dioxide": {
      "date": "Dec 31, 2023",
      "count": {
        "metric_tons": 895,
        "kilograms": 895000
      }
    },
    "plume": {
      "emission": "Moderate",
      "height": {
        "meters": 500,
        "feet": 1640.5
      },
      "drift_direction": [
        "West-Southwest",
        "Southwest"
      ]
    },
    "ground_deformation": "Short-term inflation of the edifice",
    "alert_level": {
      "level": 2,
      "remarks": "Decreased Unrest"
    },
    "url": "https://phivolcs.dost.gov.ph/volcano-hazard/volcano-bulletin2/mayon-volcano/22105-mayon-volcano-summary-of-24hr-observation-05-january-2024-12-00-am"
  },
  {
    "date": "Jan 6, 2024",
    "observation_period": "12AM - 12AM",
    "eruption": {
      "count": 0,
      "type": null,
      "duration_in_seconds": null
    },
    "seismicity": {
      "volcanic_earthquakes": 0,
      "rockfall_events": 1
    },
    "crater_glow": "Fair (naked eye)",
    "sulfur_dioxide": {
      "date": "Dec 31, 2023",
      "count": {
        "metric_tons": 895,
        "kilograms": 895000
      }
    },
    "plume": {
      "emission": "Obscured",
      "height": {
        "meters": "Obscured",
        "feet": null
      },
      "drift_direction": null
    },
    "ground_deformation": "Short-term inflation of the edifice",
    "alert_level": {
      "level": 2,
      "remarks": "Decreased Unrest"
    },
    "url": "https://phivolcs.dost.gov.ph/volcano-hazard/volcano-bulletin2/mayon-volcano/22125-mayon-volcano-summary-of-24hr-observation-06-january-2024-12-00-am"
  },
  {
    "date": "Jan 7, 2024",
    "observation_period": "12AM - 12AM",
    "eruption": {
      "count": 0,
      "type": null,
      "duration_in_seconds": null
    },
    "seismicity": {
      "volcanic_earthquakes": 0,
      "rockfall_events": 0
    },
    "crater_glow": "Fair (naked eye)",
    "sulfur_dioxide": {
      "date": "Dec 31, 2023",
      "count": {
        "metric_tons": 895,
        "kilograms": 895000
      }
    },
    "plume": {
      "emission": "Obscured",
      "height": {
        "meters": "Obscured",
        "feet": null
      },
      "drift_direction": null
    },
    "ground_deformation": "Short-term inflation of the edifice",
    "alert_level": {
      "level": 2,
      "remarks": "Decreased Unrest"
    },
    "url": "https://phivolcs.dost.gov.ph/volcano-hazard/volcano-bulletin2/mayon-volcano/22141-mayon-volcano-summary-of-24hr-observation-07-january-2024-12-00-am"
  },
  {
    "date": "Jan 8, 2024",
    "observation_period": "12AM - 12AM",
    "eruption": {
      "count": 0,
      "type": null,
      "duration_in_seconds": null
    },
    "seismicity": {
      "volcanic_earthquakes": 0,
      "rockfall_events": 2
    },
    "crater_glow": "Obscured",
    "sulfur_dioxide": {
      "date": "Dec 31, 2023",
      "count": {
        "metric_tons": 895,
        "kilograms": 895000
      }
    },
    "plume": {
      "emission": "Obscured",
      "height": {
        "meters": "Obscured",
        "feet": null
      },
      "drift_direction": null
    },
    "ground_deformation": "Short-term inflation of the edifice",
    "alert_level": {
      "level": 2,
      "remarks": "Decreased Unrest"
    },
    "url": "https://phivolcs.dost.gov.ph/volcano-hazard/volcano-bulletin2/mayon-volcano/22157-mayon-volcano-summary-of-24hr-observation-08-january-2024-12-00-am"
  },
  {
    "date": "Jan 9, 2024",
    "observation_period": "12AM - 12AM",
    "eruption": {
      "count": 0,
      "type": null,
      "duration_in_seconds": null
    },
    "seismicity": {
      "volcanic_earthquakes": 0,
      "rockfall_events": 7
    },
    "crater_glow": "Obscured",
    "sulfur_dioxide": {
      "date": "Dec 31, 2023",
      "count": {
        "metric_tons": 895,
        "kilograms": 895000
      }
    },
    "plume": {
      "emission": "Obscured",
      "height": {
        "meters": "Obscured",
        "feet": null
      },
      "drift_direction": null
    },
    "ground_deformation": "Short-term inflation of the edifice",
    "alert_level": {
      "level": 2,
      "remarks": "Decreased Unrest"
    },
    "url": "https://phivolcs.dost.gov.ph/volcano-hazard/volcano-bulletin2/mayon-volcano/22177-mayon-volcano-summary-of-24hr-observation-09-january-2024-12-00-am"
  },
  {
    "date": "Jan 10, 2024",
    "observation_period": "12AM - 12AM",
    "eruption": {
      "count": 0,
      "type": null,
      "duration_in_seconds": null
    },
    "seismicity": {
      "volcanic_earthquakes": 0,
      "rockfall_events": 1
    },
    "crater_glow": null,
    "sulfur_dioxide": {
      "date": "Jan 9, 2024",
      "count": {
        "metric_tons": 1523,
        "kilograms": 1523000
      }
    },
    "plume": {
      "emission": "Moderate",
      "height": {
        "meters": 500,
        "feet": 1640.5
      },
      "drift_direction": [
        "General West"
      ]
    },
    "ground_deformation": "Short-term inflation of the edifice",
    "alert_level": {
      "level": 2,
      "remarks": "Decreased Unrest"
    },
    "url": "https://phivolcs.dost.gov.ph/volcano-hazard/volcano-bulletin2/mayon-volcano/22193-mayon-volcano-summary-of-24hr-observation-10-january-2024-12-00-am"
  },
  {
    "date": "Jan 11, 2024",
    "observation_period": "12AM - 12AM",
    "eruption": {
      "count": 0,
      "type": null,
      "duration_in_seconds": null
    },
    "seismicity": {
      "volcanic_earthquakes": 0,
      "rockfall_events": 1
    },
    "crater_glow": "Fair (naked eye)",
    "sulfur_dioxide": {
      "date": "Jan 9, 2024",
      "count": {
        "metric_tons": 1523,
        "kilograms": 1523000
      }
    },
    "plume": {
      "emission": "Moderate",
      "height": {
        "meters": 500,
        "feet": 1640.5
      },
      "drift_direction": [
        "Southwest"
      ]
    },
    "ground_deformation": "Short-term inflation of the edifice",
    "alert_level": {
      "level": 2,
      "remarks": "Decreased Unrest"
    },
    "url": "https://phivolcs.dost.gov.ph/volcano-hazard/volcano-bulletin2/mayon-volcano/22209-mayon-volcano-summary-of-24hr-observation-11-january-2024-12-00-am"
  },
  {
    "date": "Jan 12, 2024",
    "observation_period": "12AM - 12AM",
    "eruption": {
      "count": 0,
      "type": null,
      "duration_in_seconds": null
    },
    "seismicity": {
      "volcanic_earthquakes": 1,
      "rockfall_events": 0
    },
    "crater_glow": "Fair (naked eye)",
    "sulfur_dioxide": {
      "date": "Jan 9, 2024",
      "count": {
        "metric_tons": 1523,
        "kilograms": 1523000
      }
    },
    "plume": {
      "emission": "Moderate",
      "height": {
        "meters": null,
        "feet": null
      },
      "drift_direction": [
        "Southwest",
        "West-Northwest",
        "West-Southwest"
      ]
    },
    "ground_deformation": "Short-term inflation of the edifice",
    "alert_level": {
      "level": 2,
      "remarks": "Decreased Unrest"
    },
    "url": "https://phivolcs.dost.gov.ph/volcano-hazard/volcano-bulletin2/mayon-volcano/22231-mayon-volcano-summary-of-24hr-observation-12-january-2024-12-00-am"
  },
  {
    "date": "Jan 13, 2024",
    "observation_period": "12AM - 12AM",
    "eruption": {
      "count": 0,
      "type": null,
      "duration_in_seconds": null
    },
    "seismicity": {
      "volcanic_earthquakes": 0,
      "rockfall_events": 0
    },
    "crater_glow": null,
    "sulfur_dioxide": {
      "date": "Jan 9, 2024",
      "count": {
        "metric_tons": 1523,
        "kilograms": 1523000
      }
    },
    "plume": {
      "emission": "Obscured",
      "height": {
        "meters": "Obscured",
        "feet": null
      },
      "drift_direction": null
    },
    "ground_deformation": "Short-term inflation of the edifice",
    "alert_level": {
      "level": 2,
      "remarks": "Decreased Unrest"
    },
    "url": "https://phivolcs.dost.gov.ph/volcano-hazard/volcano-bulletin2/mayon-volcano/22249-mayon-volcano-summary-of-24hr-observation-13-january-2024-12-00-am"
  },
  {
    "date": "Jan 14, 2024",
    "observation_period": "12AM - 12AM",
    "eruption": {
      "count": 0,
      "type": null,
      "duration_in_seconds": null
    },
    "seismicity": {
      "volcanic_earthquakes": 0,
      "rockfall_events": 0
    },
    "crater_glow": "Fair (naked eye)",
    "sulfur_dioxide": {
      "date": "Jan 9, 2024",
      "count": {
        "metric_tons": 1523,
        "kilograms": 1523000
      }
    },
    "plume": {
      "emission": "Moderate",
      "height": {
        "meters": null,
        "feet": null
      },
      "drift_direction": [
        "West-Southwest",
        "West-Northwest"
      ]
    },
    "ground_deformation": "Short-term inflation of the edifice",
    "alert_level": {
      "level": 2,
      "remarks": "Decreased Unrest"
    },
    "url": "https://phivolcs.dost.gov.ph/volcano-hazard/volcano-bulletin2/mayon-volcano/22265-mayon-volcano-summary-of-24hr-observation-14-january-2024-12-00-am"
  },
  {
    "date": "Jan 15, 2024",
    "observation_period": "12AM - 12AM",
    "eruption": {
      "count": 0,
      "type": null,
      "duration_in_seconds": null
    },
    "seismicity": {
      "volcanic_earthquakes": 0,
      "rockfall_events": 0
    },
    "crater_glow": "Fair (naked eye)",
    "sulfur_dioxide": {
      "date": "Jan 9, 2024",
      "count": {
        "metric_tons": 1523,
        "kilograms": 1523000
      }
    },
    "plume": {
      "emission": "Moderate",
      "height": {
        "meters": null,
        "feet": null
      },
      "drift_direction": [
        "West-Southwest",
        "Southwest"
      ]
    },
    "ground_deformation": "Short-term inflation of the edifice",
    "alert_level": {
      "level": 2,
      "remarks": "Decreased Unrest"
    },
    "url": "https://phivolcs.dost.gov.ph/volcano-hazard/volcano-bulletin2/mayon-volcano/22281-mayon-volcano-summary-of-24hr-observation-15-january-2024-12-00-am"
  },
  {
    "date": "Jan 16, 2024",
    "observation_period": "12AM - 12AM",
    "eruption": {
      "count": 0,
      "type": null,
      "duration_in_seconds": null
    },
    "seismicity": {
      "volcanic_earthquakes": 0,
      "rockfall_events": 0
    },
    "crater_glow": "Fair (naked eye)",
    "sulfur_dioxide": {
      "date": "Jan 15, 2024",
      "count": {
        "metric_tons": 1758,
        "kilograms": 1758000
      }
    },
    "plume": {
      "emission": "Moderate",
      "height": {
        "meters": null,
        "feet": null
      },
      "drift_direction": [
        "Southwest"
      ]
    },
    "ground_deformation": "Short-term inflation of the edifice",
    "alert_level": {
      "level": 2,
      "remarks": "Decreased Unrest"
    },
    "url": "https://phivolcs.dost.gov.ph/volcano-hazard/volcano-bulletin2/mayon-volcano/22307-mayon-volcano-summary-of-24hr-observation-16-january-2024-12-00-am"
  },
  {
    "date": "Jan 17, 2024",
    "observation_period": "12AM - 12AM",
    "eruption": {
      "count": 0,
      "type": null,
      "duration_in_seconds": null
    },
    "seismicity": {
      "volcanic_earthquakes": 0,
      "rockfall_events": 0
    },
    "crater_glow": "Fair (naked eye)",
    "sulfur_dioxide": {
      "date": "Jan 15, 2024",
      "count": {
        "metric_tons": 1758,
        "kilograms": 1758000
      }
    },
    "plume": {
      "emission": "Moderate",
      "height": {
        "meters": null,
        "feet": null
      },
      "drift_direction": [
        "General West"
      ]
    },
    "ground_deformation": "Short-term inflation of the edifice",
    "alert_level": {
      "level": 2,
      "remarks": "Decreased Unrest"
    },
    "url": "https://phivolcs.dost.gov.ph/volcano-hazard/volcano-bulletin2/mayon-volcano/22325-mayon-volcano-summary-of-24hr-observation-17-january-2024-12-00-am"
  },
  {
    "date": "Jan 18, 2024",
    "observation_period": "12AM - 12AM",
    "eruption": {
      "count": 0,
      "type": null,
      "duration_in_seconds": null
    },
    "seismicity": {
      "volcanic_earthquakes": 0,
      "rockfall_events": 0
    },
    "crater_glow": null,
    "sulfur_dioxide": {
      "date": "Jan 17, 2024",
      "count": {
        "metric_tons": 1684,
        "kilograms": 1684000
      }
    },
    "plume": {
      "emission": "Obscured",
      "height": {
        "meters": "Obscured",
        "feet": null
      },
      "drift_direction": null
    },
    "ground_deformation": "Short-term inflation of the edifice",
    "alert_level": {
      "level": 2,
      "remarks": "Decreased Unrest"
    },
    "url": "https://phivolcs.dost.gov.ph/volcano-hazard/volcano-bulletin2/mayon-volcano/22343-mayon-volcano-summary-of-24hr-observation-18-january-2024-12-00-am"
  },
  {
    "date": "Jan 19, 2024",
    "observation_period": "12AM - 12AM",
    "eruption": {
      "count": 0,
      "type": null,
      "duration_in_seconds": null
    },
    "seismicity": {
      "volcanic_earthquakes": 0,
      "rockfall_events": 0
    },
    "crater_glow": "Obscured",
    "sulfur_dioxide": {
      "date": "Jan 17, 2024",
      "count": {
        "metric_tons": 1684,
        "kilograms": 1684000
      }
    },
    "plume": {
      "emission": "Moderate",
      "height": {
        "meters": null,
        "feet": null
      },
      "drift_direction": [
        "West-Northwest",
        "Northwest"
      ]
    },
    "ground_deformation": "Short-term inflation of the edifice",
    "alert_level": {
      "level": 2,
      "remarks": "Decreased Unrest"
    },
    "url": "https://phivolcs.dost.gov.ph/volcano-hazard/volcano-bulletin2/mayon-volcano/22369-mayon-volcano-summary-of-24hr-observation-19-january-2024-12-00-am"
  },
  {
    "date": "Jan 20, 2024",
    "observation_period": "12AM - 12AM",
    "eruption": {
      "count": 0,
      "type": null,
      "duration_in_seconds": null
    },
    "seismicity": {
      "volcanic_earthquakes": 1,
      "rockfall_events": 1
    },
    "crater_glow": "Fair (naked eye)",
    "sulfur_dioxide": {
      "date": "Jan 17, 2024",
      "count": {
        "metric_tons": 1684,
        "kilograms": 1684000
      }
    },
    "plume": {
      "emission": "Moderate",
      "height": {
        "meters": null,
        "feet": null
      },
      "drift_direction": [
        "West-Northwest"
      ]
    },
    "ground_deformation": "Short-term inflation of the edifice",
    "alert_level": {
      "level": 2,
      "remarks": "Decreased Unrest"
    },
    "url": "https://phivolcs.dost.gov.ph/volcano-hazard/volcano-bulletin2/mayon-volcano/22395-mayon-volcano-summary-of-24hr-observation-20-january-2024-12-00-am"
  },
  {
    "date": "Jan 21, 2024",
    "observation_period": "12AM - 12AM",
    "eruption": {
      "count": 0,
      "type": null,
      "duration_in_seconds": null
    },
    "seismicity": {
      "volcanic_earthquakes": 1,
      "rockfall_events": 0
    },
    "crater_glow": "Fair (naked eye)",
    "sulfur_dioxide": {
      "date": "Jan 17, 2024",
      "count": {
        "metric_tons": 1684,
        "kilograms": 1684000
      }
    },
    "plume": {
      "emission": "Moderate",
      "height": {
        "meters": null,
        "feet": null
      },
      "drift_direction": [
        "West-Northwest"
      ]
    },
    "ground_deformation": "Short-term inflation of the edifice",
    "alert_level": {
      "level": 2,
      "remarks": "Decreased Unrest"
    },
    "url": "https://phivolcs.dost.gov.ph/volcano-hazard/volcano-bulletin2/mayon-volcano/22411-mayon-volcano-summary-of-24hr-observation-21-january-2024-12-00-am"
  },
  {
    "date": "Jan 22, 2024",
    "observation_period": "12AM - 12AM",
    "eruption": {
      "count": 0,
      "type": null,
      "duration_in_seconds": null
    },
    "seismicity": {
      "volcanic_earthquakes": 0,
      "rockfall_events": 1
    },
    "crater_glow": "Fair (naked eye)",
    "sulfur_dioxide": {
      "date": "Jan 17, 2024",
      "count": {
        "metric_tons": 1684,
        "kilograms": 1684000
      }
    },
    "plume": {
      "emission": "Obscured",
      "height": {
        "meters": "Obscured",
        "feet": null
      },
      "drift_direction": null
    },
    "ground_deformation": "Short-term inflation of the edifice",
    "alert_level": {
      "level": 2,
      "remarks": "Decreased Unrest"
    },
    "url": "https://phivolcs.dost.gov.ph/volcano-hazard/volcano-bulletin2/mayon-volcano/22427-mayon-volcano-summary-of-24hr-observation-22-january-2024-12-00-am"
  },
  {
    "date": "Jan 23, 2024",
    "observation_period": "12AM - 12AM",
    "eruption": {
      "count": 0,
      "type": null,
      "duration_in_seconds": null
    },
    "seismicity": {
      "volcanic_earthquakes": 3,
      "rockfall_events": 0
    },
    "crater_glow": "Fair (naked eye)",
    "sulfur_dioxide": {
      "date": "Jan 22, 2024",
      "count": {
        "metric_tons": 2394,
        "kilograms": 2394000
      }
    },
    "plume": {
      "emission": "Moderate",
      "height": {
        "meters": null,
        "feet": null
      },
      "drift_direction": [
        "West",
        "Southwest"
      ]
    },
    "ground_deformation": "Short-term inflation of the edifice",
    "alert_level": {
      "level": 2,
      "remarks": "Decreased Unrest"
    },
    "url": "https://phivolcs.dost.gov.ph/volcano-hazard/volcano-bulletin2/mayon-volcano/22445-mayon-volcano-summary-of-24hr-observation-23-january-2024-12-00-am"
  },
  {
    "date": "Jan 24, 2024",
    "observation_period": "12AM - 12AM",
    "eruption": {
      "count": 0,
      "type": null,
      "duration_in_seconds": null
    },
    "seismicity": {
      "volcanic_earthquakes": 0,
      "rockfall_events": 0
    },
    "crater_glow": "Fair (naked eye)",
    "sulfur_dioxide": {
      "date": "Jan 23, 2024",
      "count": {
        "metric_tons": 1054,
        "kilograms": 1054000
      }
    },
    "plume": {
      "emission": "Moderate",
      "height": {
        "meters": 300,
        "feet": 984.3000000000001
      },
      "drift_direction": [
        "Southwest",
        "West-Southwest"
      ]
    },
    "ground_deformation": "Short-term inflation of the edifice",
    "alert_level": {
      "level": 2,
      "remarks": "Decreased Unrest"
    },
    "url": "https://phivolcs.dost.gov.ph/volcano-hazard/volcano-bulletin2/mayon-volcano/22463-mayon-volcano-summary-of-24hr-observation-24-january-2024-12-00-am"
  },
  {
    "date": "Jan 25, 2024",
    "observation_period": "12AM - 12AM",
    "eruption": {
      "count": 0,
      "type": null,
      "duration_in_seconds": null
    },
    "seismicity": {
      "volcanic_earthquakes": 4,
      "rockfall_events": 0
    },
    "crater_glow": null,
    "sulfur_dioxide": {
      "date": "Jan 23, 2024",
      "count": {
        "metric_tons": 1054,
        "kilograms": 1054000
      }
    },
    "plume": {
      "emission": "Moderate",
      "height": {
        "meters": null,
        "feet": null
      },
      "drift_direction": [
        "West-Southwest",
        "Southwest"
      ]
    },
    "ground_deformation": "Short-term inflation of the edifice",
    "alert_level": {
      "level": 2,
      "remarks": "Decreased Unrest"
    },
    "url": "https://phivolcs.dost.gov.ph/volcano-hazard/volcano-bulletin2/mayon-volcano/22487-mayon-volcano-summary-of-24hr-observation-25-january-2024-12-00-am"
  },
  {
    "date": "Jan 26, 2024",
    "observation_period": "12AM - 12AM",
    "eruption": {
      "count": 0,
      "type": null,
      "duration_in_seconds": null
    },
    "seismicity": {
      "volcanic_earthquakes": 1,
      "rockfall_events": 0
    },
    "crater_glow": null,
    "sulfur_dioxide": {
      "date": "Jan 23, 2024",
      "count": {
        "metric_tons": 1054,
        "kilograms": 1054000
      }
    },
    "plume": {
      "emission": "Obscured",
      "height": {
        "meters": "Obscured",
        "feet": null
      },
      "drift_direction": null
    },
    "ground_deformation": "Short-term inflation of the edifice",
    "alert_level": {
      "level": 2,
      "remarks": "Decreased Unrest"
    },
    "url": "https://phivolcs.dost.gov.ph/volcano-hazard/volcano-bulletin2/mayon-volcano/22507-mayon-volcano-summary-of-24hr-observation-26-january-2024-12-00-am"
  },
  {
    "date": "Jan 27, 2024",
    "observation_period": "12AM - 12AM",
    "eruption": {
      "count": 0,
      "type": null,
      "duration_in_seconds": null
    },
    "seismicity": {
      "volcanic_earthquakes": 0,
      "rockfall_events": 0
    },
    "crater_glow": "Fair (naked eye)",
    "sulfur_dioxide": {
      "date": "Jan 23, 2024",
      "count": {
        "metric_tons": 1054,
        "kilograms": 1054000
      }
    },
    "plume": {
      "emission": "Obscured",
      "height": {
        "meters": "Obscured",
        "feet": null
      },
      "drift_direction": null
    },
    "ground_deformation": "Short-term inflation of the edifice",
    "alert_level": {
      "level": 2,
      "remarks": "Decreased Unrest"
    },
    "url": "https://phivolcs.dost.gov.ph/volcano-hazard/volcano-bulletin2/mayon-volcano/22529-mayon-volcano-summary-of-24hr-observation-27-january-2024-12-00-am"
  },
  {
    "date": "Jan 28, 2024",
    "observation_period": "12AM - 12AM",
    "eruption": {
      "count": 0,
      "type": null,
      "duration_in_seconds": null
    },
    "seismicity": {
      "volcanic_earthquakes": 2,
      "rockfall_events": 1
    },
    "crater_glow": "Obscured",
    "sulfur_dioxide": {
      "date": "Jan 23, 2024",
      "count": {
        "metric_tons": 1054,
        "kilograms": 1054000
      }
    },
    "plume": {
      "emission": "Moderate",
      "height": {
        "meters": null,
        "feet": null
      },
      "drift_direction": [
        "Southwest",
        "West-Southwest"
      ]
    },
    "ground_deformation": "Short-term inflation of the edifice",
    "alert_level": {
      "level": 2,
      "remarks": "Decreased Unrest"
    },
    "url": "https://phivolcs.dost.gov.ph/volcano-hazard/volcano-bulletin2/mayon-volcano/22545-mayon-volcano-summary-of-24hr-observation-28-january-2024-12-00-am"
  },
  {
    "date": "Jan 29, 2024",
    "observation_period": "12AM - 12AM",
    "eruption": {
      "count": 0,
      "type": null,
      "duration_in_seconds": null
    },
    "seismicity": {
      "volcanic_earthquakes": 0,
      "rockfall_events": 0
    },
    "crater_glow": "Obscured",
    "sulfur_dioxide": {
      "date": "Jan 23, 2024",
      "count": {
        "metric_tons": 1054,
        "kilograms": 1054000
      }
    },
    "plume": {
      "emission": "Moderate",
      "height": {
        "meters": null,
        "feet": null
      },
      "drift_direction": [
        "Northwest",
        "West"
      ]
    },
    "ground_deformation": "Short-term inflation of the edifice",
    "alert_level": {
      "level": 2,
      "remarks": "Decreased Unrest"
    },
    "url": "https://phivolcs.dost.gov.ph/volcano-hazard/volcano-bulletin2/mayon-volcano/22563-mayon-volcano-summary-of-24hr-observation-29-january-2024-12-00-am"
  },
  {
    "date": "Jan 30, 2024",
    "observation_period": "12AM - 12AM",
    "eruption": {
      "count": 0,
      "type": null,
      "duration_in_seconds": null
    },
    "seismicity": {
      "volcanic_earthquakes": 0,
      "rockfall_events": 1
    },
    "crater_glow": "Fair (naked eye)",
    "sulfur_dioxide": {
      "date": "Jan 29, 2024",
      "count": {
        "metric_tons": 1167,
        "kilograms": 1167000
      }
    },
    "plume": {
      "emission": "Obscured",
      "height": {
        "meters": "Obscured",
        "feet": null
      },
      "drift_direction": null
    },
    "ground_deformation": "Short-term inflation of the edifice",
    "alert_level": {
      "level": 2,
      "remarks": "Decreased Unrest"
    },
    "url": "https://phivolcs.dost.gov.ph/volcano-hazard/volcano-bulletin2/mayon-volcano/22581-mayon-volcano-summary-of-24hr-observation-30-january-2024-12-00-am"
  },
  {
    "date": "Jan 31, 2024",
    "observation_period": "12AM - 12AM",
    "eruption": {
      "count": 0,
      "type": null,
      "duration_in_seconds": null
    },
    "seismicity": {
      "volcanic_earthquakes": 0,
      "rockfall_events": 0
    },
    "crater_glow": "Obscured",
    "sulfur_dioxide": {
      "date": "Jan 30, 2024",
      "count": {
        "metric_tons": 1265,
        "kilograms": 1265000
      }
    },
    "plume": {
      "emission": "Moderate",
      "height": {
        "meters": 500,
        "feet": 1640.5
      },
      "drift_direction": [
        "Northwest",
        "Northeast"
      ]
    },
    "ground_deformation": "Short-term inflation of the edifice",
    "alert_level": {
      "level": 2,
      "remarks": "Decreased Unrest"
    },
    "url": "https://phivolcs.dost.gov.ph/volcano-hazard/volcano-bulletin2/mayon-volcano/22599-mayon-volcano-summary-of-24hr-observation-31-january-2024-12-00-am"
  },
  {
    "date": "Feb 1, 2024",
    "observation_period": "12AM - 12AM",
    "eruption": {
      "count": 0,
      "type": null,
      "duration_in_seconds": null
    },
    "seismicity": {
      "volcanic_earthquakes": 1,
      "rockfall_events": 1
    },
    "crater_glow": "Fair (naked eye)",
    "sulfur_dioxide": {
      "date": "Jan 30, 2024",
      "count": {
        "metric_tons": 1265,
        "kilograms": 1265000
      }
    },
    "plume": {
      "emission": "Moderate",
      "height": {
        "meters": null,
        "feet": null
      },
      "drift_direction": [
        "West-Northwest"
      ]
    },
    "ground_deformation": "Short-term inflation of the edifice",
    "alert_level": {
      "level": 2,
      "remarks": "Decreased Unrest"
    },
    "url": "https://phivolcs.dost.gov.ph/volcano-hazard/volcano-bulletin2/mayon-volcano/22619-mayon-volcano-summary-of-24hr-observation-01-february-2024-12-00-am"
  },
  {
    "date": "Feb 2, 2024",
    "observation_period": "12AM - 12AM",
    "eruption": {
      "count": 0,
      "type": null,
      "duration_in_seconds": null
    },
    "seismicity": {
      "volcanic_earthquakes": 0,
      "rockfall_events": 2
    },
    "crater_glow": "Fair (naked eye)",
    "sulfur_dioxide": {
      "date": "Jan 30, 2024",
      "count": {
        "metric_tons": 1265,
        "kilograms": 1265000
      }
    },
    "plume": {
      "emission": "Moderate",
      "height": {
        "meters": null,
        "feet": null
      },
      "drift_direction": [
        "West-Northwest"
      ]
    },
    "ground_deformation": "Short-term inflation of the edifice",
    "alert_level": {
      "level": 2,
      "remarks": "Decreased Unrest"
    },
    "url": "https://phivolcs.dost.gov.ph/volcano-hazard/volcano-bulletin2/mayon-volcano/22641-mayon-volcano-summary-of-24hr-observation-02-february-2024-12-00-am"
  },
  {
    "date": "Feb 3, 2024",
    "observation_period": "12AM - 12AM",
    "eruption": {
      "count": 0,
      "type": null,
      "duration_in_seconds": null
    },
    "seismicity": {
      "volcanic_earthquakes": 0,
      "rockfall_events": 0
    },
    "crater_glow": "Fair (naked eye)",
    "sulfur_dioxide": {
      "date": "Feb 2, 2024",
      "count": {
        "metric_tons": 621,
        "kilograms": 621000
      }
    },
    "plume": {
      "emission": "Moderate",
      "height": {
        "meters": 300,
        "feet": 984.3000000000001
      },
      "drift_direction": [
        "West-Northwest"
      ]
    },
    "ground_deformation": "Short-term inflation of the edifice",
    "alert_level": {
      "level": 2,
      "remarks": "Decreased Unrest"
    },
    "url": "https://phivolcs.dost.gov.ph/volcano-hazard/volcano-bulletin2/mayon-volcano/22667-mayon-volcano-summary-of-24hr-observation-03-february-2024-12-00-am"
  },
  {
    "date": "Feb 4, 2024",
    "observation_period": "12AM - 12AM",
    "eruption": {
      "count": 0,
      "type": null,
      "duration_in_seconds": null
    },
    "seismicity": {
      "volcanic_earthquakes": 0,
      "rockfall_events": 0
    },
    "crater_glow": "Fair (naked eye)",
    "sulfur_dioxide": {
      "date": "Feb 2, 2024",
      "count": {
        "metric_tons": 621,
        "kilograms": 621000
      }
    },
    "plume": {
      "emission": "Moderate",
      "height": {
        "meters": 200,
        "feet": 656.2
      },
      "drift_direction": [
        "General West"
      ]
    },
    "ground_deformation": "Short-term inflation of the edifice",
    "alert_level": {
      "level": 2,
      "remarks": "Decreased Unrest"
    },
    "url": "https://phivolcs.dost.gov.ph/volcano-hazard/volcano-bulletin2/mayon-volcano/22677-mayon-volcano-summary-of-24hr-observation-04-february-2024-12-00-am"
  },
  {
    "date": "Feb 5, 2024",
    "observation_period": "12AM - 12AM",
    "eruption": {
      "count": 1,
      "type": "Phreatic",
      "duration_in_seconds": 169
    },
    "seismicity": {
      "volcanic_earthquakes": 0,
      "rockfall_events": 0
    },
    "crater_glow": "Fair (naked eye)",
    "sulfur_dioxide": {
      "date": "Feb 2, 2024",
      "count": {
        "metric_tons": 621,
        "kilograms": 621000
      }
    },
    "plume": {
      "emission": "Moderate",
      "height": {
        "meters": null,
        "feet": null
      },
      "drift_direction": [
        "Northwest"
      ]
    },
    "ground_deformation": "Short-term inflation of the edifice",
    "alert_level": {
      "level": 2,
      "remarks": "Decreased Unrest"
    },
    "url": "https://phivolcs.dost.gov.ph/volcano-hazard/volcano-bulletin2/mayon-volcano/22699-mayon-volcano-summary-of-24hr-observation-05-february-2024-12-00-am"
  },
  {
    "date": "Feb 6, 2024",
    "observation_period": "12AM - 12 AM",
    "eruption": {
      "count": 0,
      "type": null,
      "duration_in_seconds": null
    },
    "seismicity": {
      "volcanic_earthquakes": 1,
      "rockfall_events": 1
    },
    "crater_glow": "Obscured",
    "sulfur_dioxide": {
      "date": "Feb 5, 2024",
      "count": {
        "metric_tons": 702,
        "kilograms": 702000
      }
    },
    "plume": {
      "emission": "Moderate",
      "height": {
        "meters": null,
        "feet": null
      },
      "drift_direction": [
        "West-Southwest"
      ]
    },
    "ground_deformation": "Short-term inflation of the edifice",
    "alert_level": {
      "level": 2,
      "remarks": "Decreased Unrest"
    },
    "url": "https://phivolcs.dost.gov.ph/volcano-hazard/volcano-bulletin2/mayon-volcano/22717-mayon-volcano-summary-of-24hr-observation-06-february-2024-12-00-am"
  },
  {
    "date": "Feb 7, 2024",
    "observation_period": "12AM - 12 AM",
    "eruption": {
      "count": 0,
      "type": null,
      "duration_in_seconds": null
    },
    "seismicity": {
      "volcanic_earthquakes": 0,
      "rockfall_events": 2
    },
    "crater_glow": "Fair (naked eye)",
    "sulfur_dioxide": {
      "date": "Feb 5, 2024",
      "count": {
        "metric_tons": 702,
        "kilograms": 702000
      }
    },
    "plume": {
      "emission": "Moderate",
      "height": {
        "meters": null,
        "feet": null
      },
      "drift_direction": [
        "West-Northwest"
      ]
    },
    "ground_deformation": "Short-term inflation of the edifice",
    "alert_level": {
      "level": 2,
      "remarks": "Decreased Unrest"
    },
    "url": "https://phivolcs.dost.gov.ph/volcano-hazard/volcano-bulletin2/mayon-volcano/22733-mayon-volcano-summary-of-24hr-observation-07-february-2024-12-00-am"
  },
  {
    "date": "Feb 8, 2024",
    "observation_period": "12AM - 12 AM",
    "eruption": {
      "count": 0,
      "type": null,
      "duration_in_seconds": null
    },
    "seismicity": {
      "volcanic_earthquakes": 1,
      "rockfall_events": 0
    },
    "crater_glow": "Fair (naked eye)",
    "sulfur_dioxide": {
      "date": "Feb 5, 2024",
      "count": {
        "metric_tons": 702,
        "kilograms": 702000
      }
    },
    "plume": {
      "emission": "Moderate",
      "height": {
        "meters": 500,
        "feet": 1640.5
      },
      "drift_direction": [
        "West-Northwest",
        "West-Southwest",
        "Southwest",
        "South-Southeast"
      ]
    },
    "ground_deformation": "Short-term inflation of the edifice",
    "alert_level": {
      "level": 2,
      "remarks": "Decreased Unrest"
    },
    "url": "https://phivolcs.dost.gov.ph/volcano-hazard/volcano-bulletin2/mayon-volcano/22757-mayon-volcano-summary-of-24hr-observation-08-february-2024-12-00-am"
  },
  {
    "date": "Feb 9, 2024",
    "observation_period": "12AM - 12 AM",
    "eruption": {
      "count": 0,
      "type": null,
      "duration_in_seconds": null
    },
    "seismicity": {
      "volcanic_earthquakes": 6,
      "rockfall_events": 0
    },
    "crater_glow": "Fair (naked eye)",
    "sulfur_dioxide": {
      "date": "Feb 8, 2024",
      "count": {
        "metric_tons": 555,
        "kilograms": 555000
      }
    },
    "plume": {
      "emission": "Moderate",
      "height": {
        "meters": 500,
        "feet": 1640.5
      },
      "drift_direction": [
        "General North",
        "West-Southwest"
      ]
    },
    "ground_deformation": "Short-term inflation of the edifice",
    "alert_level": {
      "level": 2,
      "remarks": "Decreased Unrest"
    },
    "url": "https://phivolcs.dost.gov.ph/volcano-hazard/volcano-bulletin2/mayon-volcano/22775-mayon-volcano-summary-of-24hr-observation-09-february-2024-12-00-am"
  },
  {
    "date": "Feb 10, 2024",
    "observation_period": "12AM - 12 AM",
    "eruption": {
      "count": 0,
      "type": null,
      "duration_in_seconds": null
    },
    "seismicity": {
      "volcanic_earthquakes": 2,
      "rockfall_events": 0
    },
    "crater_glow": "Obscured",
    "sulfur_dioxide": {
      "date": "Feb 8, 2024",
      "count": {
        "metric_tons": 555,
        "kilograms": 555000
      }
    },
    "plume": {
      "emission": "Moderate",
      "height": {
        "meters": 200,
        "feet": 656.2
      },
      "drift_direction": [
        "West-Northwest"
      ]
    },
    "ground_deformation": "Short-term inflation of the edifice",
    "alert_level": {
      "level": 2,
      "remarks": "Decreased Unrest"
    },
    "url": "https://phivolcs.dost.gov.ph/volcano-hazard/volcano-bulletin2/mayon-volcano/22791-mayon-volcano-summary-of-24hr-observation-10-february-2024-12-00-am"
  },
  {
    "date": "Feb 11, 2024",
    "observation_period": "12AM - 12 AM",
    "eruption": {
      "count": 0,
      "type": null,
      "duration_in_seconds": null
    },
    "seismicity": {
      "volcanic_earthquakes": 0,
      "rockfall_events": 0
    },
    "crater_glow": "Obscured",
    "sulfur_dioxide": {
      "date": "Feb 10, 2024",
      "count": {
        "metric_tons": 1875,
        "kilograms": 1875000
      }
    },
    "plume": {
      "emission": "Moderate",
      "height": {
        "meters": null,
        "feet": null
      },
      "drift_direction": [
        "West-Northwest"
      ]
    },
    "ground_deformation": "Short-term inflation of the edifice",
    "alert_level": {
      "level": 2,
      "remarks": "Decreased Unrest"
    },
    "url": "https://phivolcs.dost.gov.ph/volcano-hazard/volcano-bulletin2/mayon-volcano/22807-mayon-volcano-summary-of-24hr-observation-11-february-2024-12-00-am"
  },
  {
    "date": "Feb 12, 2024",
    "observation_period": "12AM - 12 AM",
    "eruption": {
      "count": 0,
      "type": null,
      "duration_in_seconds": null
    },
    "seismicity": {
      "volcanic_earthquakes": 0,
      "rockfall_events": 1
    },
    "crater_glow": "Faint (visible via telescope only)",
    "sulfur_dioxide": {
      "date": "Feb 10, 2024",
      "count": {
        "metric_tons": 1875,
        "kilograms": 1875000
      }
    },
    "plume": {
      "emission": "Moderate",
      "height": {
        "meters": null,
        "feet": null
      },
      "drift_direction": [
        "West-Southwest"
      ]
    },
    "ground_deformation": "Short-term inflation of the edifice",
    "alert_level": {
      "level": 2,
      "remarks": "Decreased Unrest"
    },
    "url": "https://phivolcs.dost.gov.ph/volcano-hazard/volcano-bulletin2/mayon-volcano/22823-mayon-volcano-summary-of-24hr-observation-12-february-2024-12-00-am"
  },
  {
    "date": "Feb 13, 2024",
    "observation_period": "12AM - 12 AM",
    "eruption": {
      "count": 0,
      "type": null,
      "duration_in_seconds": null
    },
    "seismicity": {
      "volcanic_earthquakes": 0,
      "rockfall_events": 0
    },
    "crater_glow": "Faint (visible via telescope only)",
    "sulfur_dioxide": {
      "date": "Feb 10, 2024",
      "count": {
        "metric_tons": 1875,
        "kilograms": 1875000
      }
    },
    "plume": {
      "emission": "Obscured",
      "height": {
        "meters": "Obscured",
        "feet": null
      },
      "drift_direction": null
    },
    "ground_deformation": "Short-term inflation of the edifice",
    "alert_level": {
      "level": 2,
      "remarks": "Decreased Unrest"
    },
    "url": "https://phivolcs.dost.gov.ph/volcano-hazard/volcano-bulletin2/mayon-volcano/22843-mayon-volcano-summary-of-24hr-observation-13-february-2024-12-00-am"
  },
  {
    "date": "Feb 14, 2024",
    "observation_period": "12AM - 12 AM",
    "eruption": {
      "count": 0,
      "type": null,
      "duration_in_seconds": null
    },
    "seismicity": {
      "volcanic_earthquakes": 0,
      "rockfall_events": 1
    },
    "crater_glow": "Faint (visible via telescope only)",
    "sulfur_dioxide": {
      "date": "Feb 10, 2024",
      "count": {
        "metric_tons": 1875,
        "kilograms": 1875000
      }
    },
    "plume": {
      "emission": "Obscured",
      "height": {
        "meters": "Obscured",
        "feet": null
      },
      "drift_direction": null
    },
    "ground_deformation": "Short-term inflation of the edifice",
    "alert_level": {
      "level": 2,
      "remarks": "Decreased Unrest"
    },
    "url": "https://phivolcs.dost.gov.ph/volcano-hazard/volcano-bulletin2/mayon-volcano/22863-mayon-volcano-summary-of-24hr-observation-14-february-2024-12-00-am"
  },
  {
    "date": "Feb 15, 2024",
    "observation_period": "12AM - 12 AM",
    "eruption": {
      "count": 0,
      "type": null,
      "duration_in_seconds": null
    },
    "seismicity": {
      "volcanic_earthquakes": 1,
      "rockfall_events": 0
    },
    "crater_glow": "Obscured",
    "sulfur_dioxide": {
      "date": "Feb 10, 2024",
      "count": {
        "metric_tons": 1875,
        "kilograms": 1875000
      }
    },
    "plume": {
      "emission": "Obscured",
      "height": {
        "meters": "Obscured",
        "feet": null
      },
      "drift_direction": null
    },
    "ground_deformation": "Short-term inflation of the edifice",
    "alert_level": {
      "level": 2,
      "remarks": "Decreased Unrest"
    },
    "url": "https://phivolcs.dost.gov.ph/volcano-hazard/volcano-bulletin2/mayon-volcano/22881-mayon-volcano-summary-of-24hr-observation-15-february-2024-12-00-am"
  },
  {
    "date": "Feb 16, 2024",
    "observation_period": "12AM - 12 AM",
    "eruption": {
      "count": 0,
      "type": null,
      "duration_in_seconds": null
    },
    "seismicity": {
      "volcanic_earthquakes": 1,
      "rockfall_events": 0
    },
    "crater_glow": "Fair (naked eye)",
    "sulfur_dioxide": {
      "date": "Feb 10, 2024",
      "count": {
        "metric_tons": 1875,
        "kilograms": 1875000
      }
    },
    "plume": {
      "emission": "Moderate",
      "height": {
        "meters": null,
        "feet": null
      },
      "drift_direction": [
        "West-Northwest"
      ]
    },
    "ground_deformation": "Short-term inflation of the edifice",
    "alert_level": {
      "level": 2,
      "remarks": "Decreased Unrest"
    },
    "url": "https://phivolcs.dost.gov.ph/volcano-hazard/volcano-bulletin2/mayon-volcano/22901-mayon-volcano-summary-of-24hr-observation-16-february-2024-12-00-am"
  },
  {
    "date": "Feb 17, 2024",
    "observation_period": "12AM - 12 AM",
    "eruption": {
      "count": 0,
      "type": null,
      "duration_in_seconds": null
    },
    "seismicity": {
      "volcanic_earthquakes": 0,
      "rockfall_events": 0
    },
    "crater_glow": "Faint (visible via telescope only)",
    "sulfur_dioxide": {
      "date": "Feb 10, 2024",
      "count": {
        "metric_tons": 1875,
        "kilograms": 1875000
      }
    },
    "plume": {
      "emission": "Moderate",
      "height": {
        "meters": null,
        "feet": null
      },
      "drift_direction": [
        "Southwest"
      ]
    },
    "ground_deformation": "Short-term inflation of the edifice",
    "alert_level": {
      "level": 2,
      "remarks": "Decreased Unrest"
    },
    "url": "https://phivolcs.dost.gov.ph/volcano-hazard/volcano-bulletin2/mayon-volcano/22923-mayon-volcano-summary-of-24hr-observation-17-february-2024-12-00-am"
  },
  {
    "date": "Feb 18, 2024",
    "observation_period": "12AM - 12 AM",
    "eruption": {
      "count": 0,
      "type": null,
      "duration_in_seconds": null
    },
    "seismicity": {
      "volcanic_earthquakes": 0,
      "rockfall_events": 0
    },
    "crater_glow": "Faint (visible via telescope only)",
    "sulfur_dioxide": {
      "date": "Feb 10, 2024",
      "count": {
        "metric_tons": 1875,
        "kilograms": 1875000
      }
    },
    "plume": {
      "emission": "Moderate",
      "height": {
        "meters": null,
        "feet": null
      },
      "drift_direction": [
        "Northwest"
      ]
    },
    "ground_deformation": "Short-term inflation of the edifice",
    "alert_level": {
      "level": 2,
      "remarks": "Decreased Unrest"
    },
    "url": "https://phivolcs.dost.gov.ph/volcano-hazard/volcano-bulletin2/mayon-volcano/22939-mayon-volcano-summary-of-24hr-observation-18-february-2024-12-00-am"
  },
  {
    "date": "Feb 19, 2024",
    "observation_period": "12AM - 12 AM",
    "eruption": {
      "count": 0,
      "type": null,
      "duration_in_seconds": null
    },
    "seismicity": {
      "volcanic_earthquakes": 0,
      "rockfall_events": 0
    },
    "crater_glow": "Obscured",
    "sulfur_dioxide": {
      "date": "Feb 10, 2024",
      "count": {
        "metric_tons": 1875,
        "kilograms": 1875000
      }
    },
    "plume": {
      "emission": "Obscured",
      "height": {
        "meters": "obscured",
        "feet": null
      },
      "drift_direction": null
    },
    "ground_deformation": "Short-term inflation of the edifice",
    "alert_level": {
      "level": 2,
      "remarks": "Decreased Unrest"
    },
    "url": "https://phivolcs.dost.gov.ph/volcano-hazard/volcano-bulletin2/mayon-volcano/22955-mayon-volcano-summary-of-24hr-observation-19-february-2024-12-00-am"
  },
  {
    "date": "Feb 20, 2024",
    "observation_period": "12AM - 12 AM",
    "eruption": {
      "count": 0,
      "type": null,
      "duration_in_seconds": null
    },
    "seismicity": {
      "volcanic_earthquakes": 2,
      "rockfall_events": 0
    },
    "crater_glow": "Faint (visible via telescope only)",
    "sulfur_dioxide": {
      "date": "Feb 19, 2024",
      "count": {
        "metric_tons": 819,
        "kilograms": 819000
      }
    },
    "plume": {
      "emission": "Moderate",
      "height": {
        "meters": null,
        "feet": null
      },
      "drift_direction": [
        "General West"
      ]
    },
    "ground_deformation": "Short-term inflation of the edifice",
    "alert_level": {
      "level": 2,
      "remarks": "Decreased Unrest"
    },
    "url": "https://phivolcs.dost.gov.ph/volcano-hazard/volcano-bulletin2/mayon-volcano/22981-mayon-volcano-summary-of-24hr-observation-20-february-2024-12-00-am"
  },
  {
    "date": "Feb 21, 2024",
    "observation_period": "12AM - 12 AM",
    "eruption": {
      "count": 0,
      "type": null,
      "duration_in_seconds": null
    },
    "seismicity": {
      "volcanic_earthquakes": 0,
      "rockfall_events": 0
    },
    "crater_glow": "Faint (visible via telescope only)",
    "sulfur_dioxide": {
      "date": "Feb 20, 2024",
      "count": {
        "metric_tons": 597,
        "kilograms": 597000
      }
    },
    "plume": {
      "emission": "Moderate",
      "height": {
        "meters": null,
        "feet": null
      },
      "drift_direction": [
        "West-Northwest",
        "West-Southwest"
      ]
    },
    "ground_deformation": "Short-term inflation of the edifice",
    "alert_level": {
      "level": 2,
      "remarks": "Decreased Unrest"
    },
    "url": "https://phivolcs.dost.gov.ph/volcano-hazard/volcano-bulletin2/mayon-volcano/23003-mayon-volcano-summary-of-24hr-observation-21-february-2024-12-00-am"
  },
  {
    "date": "Feb 22, 2024",
    "observation_period": "12AM - 12 AM",
    "eruption": {
      "count": 0,
      "type": null,
      "duration_in_seconds": null
    },
    "seismicity": {
      "volcanic_earthquakes": 3,
      "rockfall_events": 0
    },
    "crater_glow": "Faint (visible via telescope only)",
    "sulfur_dioxide": {
      "date": "Feb 21, 2024",
      "count": {
        "metric_tons": 845,
        "kilograms": 845000
      }
    },
    "plume": {
      "emission": "Weak",
      "height": {
        "meters": null,
        "feet": null
      },
      "drift_direction": [
        "West-Northwest"
      ]
    },
    "ground_deformation": "Short-term inflation of the edifice",
    "alert_level": {
      "level": 2,
      "remarks": "Decreased Unrest"
    },
    "url": "https://phivolcs.dost.gov.ph/volcano-hazard/volcano-bulletin2/mayon-volcano/23019-mayon-volcano-summary-of-24hr-observation-22-february-2024-12-00-am"
  },
  {
    "date": "Feb 23, 2024",
    "observation_period": "12AM - 12 AM",
    "eruption": {
      "count": 0,
      "type": null,
      "duration_in_seconds": null
    },
    "seismicity": {
      "volcanic_earthquakes": 0,
      "rockfall_events": 0
    },
    "crater_glow": "Faint (visible via telescope only)",
    "sulfur_dioxide": {
      "date": "Feb 21, 2024",
      "count": {
        "metric_tons": 845,
        "kilograms": 845000
      }
    },
    "plume": {
      "emission": "Moderate",
      "height": {
        "meters": null,
        "feet": null
      },
      "drift_direction": [
        "West-Southwest",
        "West-Northwest"
      ]
    },
    "ground_deformation": "Short-term inflation of the edifice",
    "alert_level": {
      "level": 2,
      "remarks": "Decreased Unrest"
    },
    "url": "https://phivolcs.dost.gov.ph/volcano-hazard/volcano-bulletin2/mayon-volcano/23041-mayon-volcano-summary-of-24hr-observation-23-february-2024-12-00-am"
  },
  {
    "date": "Feb 24, 2024",
    "observation_period": "12AM - 12 AM",
    "eruption": {
      "count": 0,
      "type": null,
      "duration_in_seconds": null
    },
    "seismicity": {
      "volcanic_earthquakes": 0,
      "rockfall_events": 0
    },
    "crater_glow": "Obscured",
    "sulfur_dioxide": {
      "date": "Feb 21, 2024",
      "count": {
        "metric_tons": 845,
        "kilograms": 845000
      }
    },
    "plume": {
      "emission": "Moderate",
      "height": {
        "meters": null,
        "feet": null
      },
      "drift_direction": [
        "Northwest",
        "West-Northwest"
      ]
    },
    "ground_deformation": "Short-term inflation of the edifice",
    "alert_level": {
      "level": 2,
      "remarks": "Decreased Unrest"
    },
    "url": "https://phivolcs.dost.gov.ph/volcano-hazard/volcano-bulletin2/mayon-volcano/23059-mayon-volcano-summary-of-24hr-observation-24-february-2024-12-00-am"
  },
  {
    "date": "Feb 25, 2024",
    "observation_period": "12AM - 12 AM",
    "eruption": {
      "count": 0,
      "type": null,
      "duration_in_seconds": null
    },
    "seismicity": {
      "volcanic_earthquakes": 1,
      "rockfall_events": 0
    },
    "crater_glow": "Obscured",
    "sulfur_dioxide": {
      "date": "Feb 21, 2024",
      "count": {
        "metric_tons": 845,
        "kilograms": 845000
      }
    },
    "plume": {
      "emission": "Moderate",
      "height": {
        "meters": null,
        "feet": null
      },
      "drift_direction": null
    },
    "ground_deformation": "Short-term inflation of the edifice",
    "alert_level": {
      "level": 2,
      "remarks": "Decreased Unrest"
    },
    "url": "https://phivolcs.dost.gov.ph/volcano-hazard/volcano-bulletin2/mayon-volcano/23075-mayon-volcano-summary-of-24hr-observation-25-february-2024-12-00-am"
  },
  {
    "date": "Feb 26, 2024",
    "observation_period": "12AM - 12 AM",
    "eruption": {
      "count": 0,
      "type": null,
      "duration_in_seconds": null
    },
    "seismicity": {
      "volcanic_earthquakes": 1,
      "rockfall_events": 1
    },
    "crater_glow": "Faint (visible via telescope only)",
    "sulfur_dioxide": {
      "date": "Feb 21, 2024",
      "count": {
        "metric_tons": 845,
        "kilograms": 845000
      }
    },
    "plume": {
      "emission": "Obscured",
      "height": {
        "meters": "Obscured",
        "feet": null
      },
      "drift_direction": null
    },
    "ground_deformation": "Short-term inflation of the edifice",
    "alert_level": {
      "level": 2,
      "remarks": "Decreased Unrest"
    },
    "url": "https://phivolcs.dost.gov.ph/volcano-hazard/volcano-bulletin2/mayon-volcano/23091-mayon-volcano-summary-of-24hr-observation-26-february-2024-12-00-am"
  },
  {
    "date": "Feb 27, 2024",
    "observation_period": "12AM - 12 AM",
    "eruption": {
      "count": 0,
      "type": null,
      "duration_in_seconds": null
    },
    "seismicity": {
      "volcanic_earthquakes": 0,
      "rockfall_events": 0
    },
    "crater_glow": "Faint (visible via telescope only)",
    "sulfur_dioxide": {
      "date": "Feb 26, 2024",
      "count": {
        "metric_tons": 1092,
        "kilograms": 1092000
      }
    },
    "plume": {
      "emission": "Moderate",
      "height": {
        "meters": null,
        "feet": null
      },
      "drift_direction": [
        "General West"
      ]
    },
    "ground_deformation": "Short-term inflation of the edifice",
    "alert_level": {
      "level": 2,
      "remarks": "Decreased Unrest"
    },
    "url": "https://phivolcs.dost.gov.ph/volcano-hazard/volcano-bulletin2/mayon-volcano/23111-mayon-volcano-summary-of-24hr-observation-27-february-2024-12-00-am"
  },
  {
    "date": "Feb 28, 2024",
    "observation_period": "12AM - 12 AM",
    "eruption": {
      "count": 0,
      "type": null,
      "duration_in_seconds": null
    },
    "seismicity": {
      "volcanic_earthquakes": 0,
      "rockfall_events": 0
    },
    "crater_glow": "Obscured",
    "sulfur_dioxide": {
      "date": "Feb 26, 2024",
      "count": {
        "metric_tons": 1092,
        "kilograms": 1092000
      }
    },
    "plume": {
      "emission": "Obscured",
      "height": {
        "meters": "Obscured",
        "feet": null
      },
      "drift_direction": null
    },
    "ground_deformation": "Short-term inflation of the edifice",
    "alert_level": {
      "level": 2,
      "remarks": "Decreased Unrest"
    },
    "url": "https://phivolcs.dost.gov.ph/volcano-hazard/volcano-bulletin2/mayon-volcano/23127-mayon-volcano-summary-of-24hr-observation-28-february-2024-12-00-am"
  },
  {
    "date": "Feb 29, 2024",
    "observation_period": "12AM - 12 AM",
    "eruption": {
      "count": 0,
      "type": null,
      "duration_in_seconds": null
    },
    "seismicity": {
      "volcanic_earthquakes": 2,
      "rockfall_events": 0
    },
    "crater_glow": "Faint (visible via telescope only)",
    "sulfur_dioxide": {
      "date": "Feb 26, 2024",
      "count": {
        "metric_tons": 1092,
        "kilograms": 1092000
      }
    },
    "plume": {
      "emission": "Moderate",
      "height": {
        "meters": null,
        "feet": null
      },
      "drift_direction": [
        "West"
      ]
    },
    "ground_deformation": "Short-term inflation of the edifice",
    "alert_level": {
      "level": 2,
      "remarks": "Decreased Unrest"
    },
    "url": "https://phivolcs.dost.gov.ph/volcano-hazard/volcano-bulletin2/mayon-volcano/23143-mayon-volcano-summary-of-24hr-observation-29-february-2024-12-00-am"
  },
  {
    "date": "Mar 1, 2024",
    "observation_period": "12AM - 12 AM",
    "eruption": {
      "count": 0,
      "type": null,
      "duration_in_seconds": null
    },
    "seismicity": {
      "volcanic_earthquakes": 1,
      "rockfall_events": 0
    },
    "crater_glow": "Faint (visible via telescope only)",
    "sulfur_dioxide": {
      "date": "Feb 26, 2024",
      "count": {
        "metric_tons": 1092,
        "kilograms": 1092000
      }
    },
    "plume": {
      "emission": "Moderate",
      "height": {
        "meters": null,
        "feet": null
      },
      "drift_direction": [
        "West-Northwest"
      ]
    },
    "ground_deformation": "Short-term inflation of the edifice",
    "alert_level": {
      "level": 2,
      "remarks": "Decreased Unrest"
    },
    "url": "https://phivolcs.dost.gov.ph/volcano-hazard/volcano-bulletin2/mayon-volcano/23171-mayon-volcano-summary-of-24hr-observation-01-march-2024-12-00-am"
  },
  {
    "date": "Mar 2, 2024",
    "observation_period": "12AM - 12 AM",
    "eruption": {
      "count": 0,
      "type": null,
      "duration_in_seconds": null
    },
    "seismicity": {
      "volcanic_earthquakes": 0,
      "rockfall_events": 1
    },
    "crater_glow": "Faint (visible via telescope only)",
    "sulfur_dioxide": {
      "date": "Feb 26, 2024",
      "count": {
        "metric_tons": 1092,
        "kilograms": 1092000
      }
    },
    "plume": {
      "emission": "Moderate",
      "height": {
        "meters": null,
        "feet": null
      },
      "drift_direction": [
        "West",
        "West-Northwest"
      ]
    },
    "ground_deformation": "Short-term inflation of the edifice",
    "alert_level": {
      "level": 2,
      "remarks": "Decreased Unrest"
    },
    "url": "https://phivolcs.dost.gov.ph/volcano-hazard/volcano-bulletin2/mayon-volcano/23189-mayon-volcano-summary-of-24hr-observation-02-march-2024-12-00-am"
  },
  {
    "date": "Mar 3, 2024",
    "observation_period": "12AM - 12 AM",
    "eruption": {
      "count": 0,
      "type": null,
      "duration_in_seconds": null
    },
    "seismicity": {
      "volcanic_earthquakes": 0,
      "rockfall_events": 0
    },
    "crater_glow": "Faint (visible via telescope only)",
    "sulfur_dioxide": {
      "date": "Feb 26, 2024",
      "count": {
        "metric_tons": 1092,
        "kilograms": 1092000
      }
    },
    "plume": {
      "emission": "Moderate",
      "height": {
        "meters": 200,
        "feet": 656.2
      },
      "drift_direction": [
        "East-Southeast. South-Southwest",
        "West"
      ]
    },
    "ground_deformation": "Short-term inflation of the edifice",
    "alert_level": {
      "level": 2,
      "remarks": "Decreased Unrest"
    },
    "url": "https://phivolcs.dost.gov.ph/volcano-hazard/volcano-bulletin2/mayon-volcano/23205-mayon-volcano-summary-of-24hr-observation-03-march-2024-12-00-am"
  }
]